Metadata-Version: 2.1
Name: demo-package-juampi
Version: 0.0.1
Summary: Say hello!
